sdl2hl/__init__.py
sdl2hl/constants.py
sdl2hl/enumtools.py
sdl2hl/error.py
sdl2hl/events.py
sdl2hl/gamecontroller.py
sdl2hl/gfx.py
sdl2hl/image.py
sdl2hl/keycode.py
sdl2hl/mixer.py
sdl2hl/pixels.py
sdl2hl/rect.py
sdl2hl/renderer.py
sdl2hl/scancode.py
sdl2hl/sdl.py
sdl2hl/surface.py
sdl2hl/timer.py
sdl2hl/ttf.py
sdl2hl/video.py
sdl2hl-0.3.5.dist-info/DESCRIPTION.rst
sdl2hl-0.3.5.dist-info/METADATA
sdl2hl-0.3.5.dist-info/RECORD
sdl2hl-0.3.5.dist-info/WHEEL
sdl2hl-0.3.5.dist-info/metadata.json
sdl2hl-0.3.5.dist-info/top_level.txt
