Metadata-Version: 2.0
Name: sdl2hl
Version: 0.3.5
Summary: A Pythonic API wrapper for SDL2.
Home-page: https://github.com/jdoda/sdl2hl
Author: Jonathan Doda
Author-email: jonathan@jdoda.ca
License: zlib
Keywords: sdl2,cffi
Platform: UNKNOWN
Classifier: Development Status :: 3 - Alpha
Classifier: Intended Audience :: Developers
Classifier: License :: OSI Approved :: zlib/libpng License
Classifier: Programming Language :: Python :: 2
Classifier: Programming Language :: Python :: 2.7
Classifier: Programming Language :: Python :: 3
Classifier: Programming Language :: Python :: 3.4
Requires-Dist: enum34 (>=1.0.0)
Requires-Dist: sdl2-cffi (>=1.0.5)
